pybirdwatcher/__init__.py
pybirdwatcher/binary.py
pybirdwatcher/cli.py
pybirdwatcher/client.py
pybirdwatcher/models.py
pybirdwatcher/version.py
pybirdwatcher/bin/birdwatcher
pybirdwatcher-0.1.0.dist-info/METADATA
pybirdwatcher-0.1.0.dist-info/WHEEL
pybirdwatcher-0.1.0.dist-info/entry_points.txt
pybirdwatcher-0.1.0.dist-info/RECORD
