Metadata-Version: 2.4
Name: pybirdwatcher
Version: 0.1.0
Summary: Python wrapper for Birdwatcher - Milvus debug and diagnostic tool
Project-URL: Homepage, https://github.com/milvus-io/birdwatcher
Project-URL: Repository, https://github.com/milvus-io/birdwatcher
Author: Milvus Team
License-Expression: Apache-2.0
Keywords: debug,diagnostic,etcd,milvus,vector-database
Classifier: Development Status :: 4 - Beta
Classifier: Intended Audience :: Developers
Classifier: License :: OSI Approved :: Apache Software License
Classifier: Operating System :: OS Independent
Classifier: Programming Language :: Python :: 3
Classifier: Programming Language :: Python :: 3.9
Classifier: Programming Language :: Python :: 3.10
Classifier: Programming Language :: Python :: 3.11
Classifier: Programming Language :: Python :: 3.12
Classifier: Topic :: Database
Classifier: Topic :: System :: Monitoring
Requires-Python: >=3.9
